{
	"dialogue": [
		{
			"sound": "",
			"speed": 0.03,
			"portrait": "bf",
			"boxState": "normal",
			"expression": "confused",
			"text": "uhh....."
		},
		{
			"sound": "",
			"speed": 0.03,
			"portrait": "bf",
			"boxState": "normal",
			"expression": "confused",
			"text": "easy, right?"
		},
		{
			"sound": "",
			"speed": 0.05,
			"portrait": "bf",
			"boxState": "normal",
			"expression": "excited",
			"text": "yeah!"
		},
		{
			"sound": "",
			"speed": 0.05,
			"portrait": "bf",
			"boxState": "normal",
			"expression": "pissed",
			"text": "i hope you can complete this next task i have"
		},
		{
			"sound": "",
			"speed": 0.05,
			"portrait": "bf",
			"boxState": "normal",
			"expression": "confused",
			"text": "which is?"
		},
		{
			"sound": "",
			"speed": 0.05,
			"portrait": "bf",
			"boxState": "normal",
			"expression": "excited",
			"text": "beat the 2nd song :)"
		},
		{
			"sound": "",
			"speed": 0.01,
			"portrait": "bf",
			"boxState": "angry",
			"expression": "confused",
			"text": "why the fuck are the song names called '1st song, 2nd song, 3rd song'"
		},
		{
			"sound": "",
			"speed": 0.05,
			"portrait": "bf",
			"boxState": "normal",
			"expression": "excited",
			"text": "too lazy to say the ACTUAL names bitch ;>"
		},
		{
			"sound": "",
			"speed": 0.05,
			"portrait": "bf",
			"boxState": "normal",
			"expression": "talk",
			"text": "that's so unswag"
		},
		{
			"sound": "",
			"speed": 0.01,
			"portrait": "bf",
			"boxState": "angry",
			"expression": "pissed",
			"text": "fuck you, let's get this task over with so i can beat your ass >:("
		},
		{
			"sound": "",
			"speed": 0.05,
			"portrait": "bf",
			"boxState": "normal",
			"expression": "shocked",
			"text": "damn, you wild for some shit now :0"
		}
	]
}